Metadata-Version: 2.1
Name: openml
Version: 0.15.0
Summary: Python API for OpenML
Author: Jan van Rijn, Arlind Kadra, Pieter Gijsbers, Neeratyoy Mallik, Sahithya Ravi, Andreas Müller, Joaquin Vanschoren , Frank Hutter
Author-email: Matthias Feurer <feurerm@informatik.uni-freiburg.de>
License: BSD 3-Clause License
Project-URL: home, https://openml.org/
Project-URL: documentation, https://openml.github.io/openml-python/
Project-URL: source, https://github.com/openml/openml-python
Classifier: Intended Audience :: Science/Research
Classifier: Intended Audience :: Developers
Classifier: License :: OSI Approved :: BSD License
Classifier: Programming Language :: Python
Classifier: Topic :: Software Development
Classifier: Topic :: Scientific/Engineering
Classifier: Operating System :: POSIX
Classifier: Operating System :: Unix
Classifier: Operating System :: MacOS
Classifier: Programming Language :: Python :: 3
Classifier: Programming Language :: Python :: 3.8
Classifier: Programming Language :: Python :: 3.9
Classifier: Programming Language :: Python :: 3.10
Classifier: Programming Language :: Python :: 3.11
Classifier: Programming Language :: Python :: 3.12
Requires-Python: >=3.8
License-File: LICENSE
Requires-Dist: liac-arff >=2.4.0
Requires-Dist: xmltodict
Requires-Dist: requests
Requires-Dist: scikit-learn >=0.18
Requires-Dist: python-dateutil
Requires-Dist: pandas >=1.0.0
Requires-Dist: scipy >=0.13.3
Requires-Dist: numpy >=1.6.2
Requires-Dist: minio
Requires-Dist: pyarrow
Requires-Dist: tqdm
Requires-Dist: packaging
Provides-Extra: docs
Requires-Dist: sphinx >=3 ; extra == 'docs'
Requires-Dist: sphinx-gallery ; extra == 'docs'
Requires-Dist: sphinx-bootstrap-theme ; extra == 'docs'
Requires-Dist: numpydoc ; extra == 'docs'
Provides-Extra: examples
Requires-Dist: matplotlib ; extra == 'examples'
Requires-Dist: jupyter ; extra == 'examples'
Requires-Dist: notebook ; extra == 'examples'
Requires-Dist: nbconvert ; extra == 'examples'
Requires-Dist: nbformat ; extra == 'examples'
Requires-Dist: jupyter-client ; extra == 'examples'
Requires-Dist: ipython ; extra == 'examples'
Requires-Dist: ipykernel ; extra == 'examples'
Requires-Dist: seaborn ; extra == 'examples'
Provides-Extra: examples_unix
Requires-Dist: fanova ; extra == 'examples_unix'
Provides-Extra: test
Requires-Dist: nbconvert ; extra == 'test'
Requires-Dist: jupyter-client ; extra == 'test'
Requires-Dist: matplotlib ; extra == 'test'
Requires-Dist: pytest ; extra == 'test'
Requires-Dist: pytest-xdist ; extra == 'test'
Requires-Dist: pytest-timeout ; extra == 'test'
Requires-Dist: nbformat ; extra == 'test'
Requires-Dist: oslo.concurrency ; extra == 'test'
Requires-Dist: flaky ; extra == 'test'
Requires-Dist: pre-commit ; extra == 'test'
Requires-Dist: pytest-cov ; extra == 'test'
Requires-Dist: pytest-rerunfailures ; extra == 'test'
Requires-Dist: mypy ; extra == 'test'
Requires-Dist: ruff ; extra == 'test'
